{
  "modules": [
    {
      "name": "audit-logs",
      "manageColumns": [
        {
          "name": "entityType",
          "label": "Module",
          "type": "string"
        },
        {
          "name": "logDescription",
          "label": "Log Description",
          "type": "string"
        },
        {
          "name": "userType",
          "label": "User Type",
          "type": "string"
        },
        {
          "name": "userRefId",
          "label": "User Name",
          "type": "string"
        },
        {
          "name": "entityRefId",
          "label": "Entity Name",
          "type": "string"
        },
        {
          "name": "actionType",
          "label": "Action Type",
          "type": "string"
        },
        {
          "name": "createdAt",
          "label": "Created Date",
          "type": "date"
        }
      ],
      "defaultColumns": [
        "entityType",
        "actionType",
        "logDescription",
        "userRefId",
        "createdAt"
      ]
    },
    {
      "name": "application",
      "manageColumns": [
        {
          "name": "applicationId",
          "label": "Application Number",
          "type": "string"
        },
        {
          "name": "status",
          "label": "Status",
          "type": "string"
        },
        {
          "name": "clientId",
          "label": "Client Name",
          "type": "modal",
          "request": {
            "method": "GET",
            "url": "client/details"
          }
        },
        {
          "name": "debtorId",
          "label": "Debtor Name",
          "type": "modal",
          "request": {
            "method": "GET",
            "url": "debtor/drawer"
          }
        },
        {
          "name": "entityType",
          "label": "Entity Type",
          "type": "string"
        },
        {
          "name": "creditLimit",
          "label": "Requested Amount",
          "type": "amount"
        },
        {
          "name": "acceptedAmount",
          "label": "Approved Amount",
          "type": "amount"
        },
        {
          "name": "requestDate",
          "label": "Requested Date",
          "type": "date"
        },
        {
          "name": "approvalOrDecliningDate",
          "label": "Approval Date",
          "type": "date"
        },
        {
          "name": "expiryDate",
          "label": "Expiry Date",
          "type": "date"
        },
        {
          "name": "createdById",
          "label": "Submitted By",
          "type": "string"
        },
        {
          "name": "outstandingAmount",
          "label": "Outstanding Amount",
          "type": "amount"
        },
        {
          "name": "orderOnHand",
          "label": "Orders on hand",
          "type": "amount"
        },
        {
          "name": "limitType",
          "label": "Limit Type",
          "type": "string"
        },
        {
          "name": "clientReference",
          "label": "Client Reference",
          "type": "string"
        },
        {
          "name": "isExtendedPaymentTerms",
          "label": "Has Extended Payment Terms",
          "type": "string"
        },
        {
          "name": "extendedPaymentTermsDetails",
          "label": "Extended Payment Terms Details",
          "type": "string"
        },
        {
          "name": "isPassedOverdueAmount",
          "label": "Has Passed Overdue Amount",
          "type": "string"
        },
        {
          "name": "passedOverdueDetails",
          "label": "Passed Overdue Details",
          "type": "string"
        },
        {
          "name": "createdAt",
          "label": "Created Date",
          "type": "date"
        },
        {
          "name": "updatedAt",
          "label": "Modified Date",
          "type": "date"
        },
        {
          "name": "comments",
          "label": "Comments",
          "type": "string"
        },
        {
          "name": "delete",
          "label": "Delete",
          "type": "icon"
        }
      ],
      "defaultColumns": [
        "applicationId",
        "status",
        "entityType",
        "clientId",
        "debtorId",
        "creditLimit",
        "requestDate",
        "createdById",
        "updatedAt",
        "comments",
        "delete"
      ]
    },
    {
      "name": "application-task",
      "manageColumns": [
        {
          "name": "priority",
          "label": "Priority",
          "type": "string"
        },
        {
          "name": "description",
          "label": "Description",
          "type": "string"
        },
        {
          "name": "comments",
          "label": "Comments",
          "type": "string"
        },
        {
          "name": "entityType",
          "label": "Entity Type",
          "type": "string"
        },
        {
          "name": "entityId",
          "label": "Entity Name",
          "type": "modal"
        },
        {
          "name": "createdById",
          "label": "Created By",
          "type": "string"
        },
        {
          "name": "assigneeId",
          "label": "Assignee",
          "type": "string"
        },
        {
          "name": "dueDate",
          "label": "Due Date",
          "type": "date"
        },
        {
          "name": "createdAt",
          "label": "Created Date",
          "type": "date"
        },
        {
          "name": "updatedAt",
          "label": "Modified Date",
          "type": "date"
        }
      ],
      "defaultColumns": [
        "priority",
        "description",
        "comments",
        "entityType",
        "assigneeId",
        "dueDate"
      ]
    },
    {
      "name": "client",
      "manageColumns": [
        {
          "name": "clientCode",
          "label": "Client Code",
          "type": "string"
        },
        {
          "name": "name",
          "label": "Name",
          "type": "string"
        },
        {
          "name": "contactNumber",
          "label": "Contact Number",
          "type": "string"
        },
        {
          "name": "riskAnalystId",
          "label": "Risk Analyst",
          "type": "string"
        },
        {
          "name": "serviceManagerId",
          "label": "Service Manager",
          "type": "string"
        },
        {
          "name": "insurerId",
          "label": "Insurer Name",
          "type": "string"
        },
        {
          "name": "fullAddress",
          "label": "Full Address",
          "type": "string"
        },
        {
          "name": "addressLine",
          "label": "Address Line",
          "type": "string"
        },
        {
          "name": "city",
          "label": "City",
          "type": "string"
        },
        {
          "name": "state",
          "label": "Country/State",
          "type": "string"
        },
        {
          "name": "country",
          "label": "Country",
          "type": "string"
        },
        {
          "name": "zipCode",
          "label": "Postcode/Zip",
          "type": "string"
        },
        {
          "name": "website",
          "label": "Website",
          "type": "string"
        },
        {
          "name": "sector",
          "label": "Sector",
          "type": "string"
        },
        {
          "name": "abn",
          "label": "ABN/NZBN",
          "type": "string"
        },
        {
          "name": "acn",
          "label": "ACN/NCN",
          "type": "string"
        },
        {
          "name": "salesPerson",
          "label": "Sales Person",
          "type": "string"
        },
        {
          "name": "referredBy",
          "label": "Referred By",
          "type": "string"
        },
        {
          "name": "inceptionDate",
          "label": "Inception Date",
          "type": "date"
        },
        {
          "name": "expiryDate",
          "label": "Expiry Date",
          "type": "date"
        },
        {
          "name": "isAutoApproveAllowed",
          "label": "AutoApprove Allowed",
          "type": "string"
        },
        {
          "name": "createdAt",
          "label": "Created Date",
          "type": "date"
        },
        {
          "name": "updatedAt",
          "label": "Modified Date",
          "type": "date"
        }
      ],
      "defaultColumns": [
        "clientCode",
        "name",
        "contactNumber",
        "riskAnalystId",
        "abn",
        "acn",
        "insurerId",
        "expiryDate"
      ]
    },
    {
      "name": "client-user",
      "manageColumns": [
        {
          "name": "name",
          "label": "Name",
          "type": "modal",
          "request": {
            "method": "GET",
            "url": "client/user-details"
          }
        },
        {
          "name": "contactNumber",
          "label": "Contact Number",
          "type": "string"
        },
        {
          "name": "department",
          "label": "Department",
          "type": "string"
        },
        {
          "name": "hasPortalAccess",
          "label": "Portal Access",
          "type": "boolean",
          "isDisabled": false,
          "request": {
            "method": "PUT",
            "url": "client/user"
          }
        },
        {
          "name": "sendDecisionLetter",
          "label": "Decision Letter",
          "type": "boolean",
          "isDisabled": false,
          "request": {
            "method": "PUT",
            "url": "client/user"
          }
        },
        {
          "name": "hasLeftCompany",
          "label": "Left Company",
          "type": "string"
        },
        {
          "name": "email",
          "label": "Email",
          "type": "string"
        },
        {
          "name": "createdAt",
          "label": "Created Date",
          "type": "date"
        },
        {
          "name": "updatedAt",
          "label": "Modified Date",
          "type": "date"
        }
      ],
      "defaultColumns": [
        "name",
        "contactNumber",
        "department",
        "hasPortalAccess",
        "email"
      ]
    },
    {
      "name": "client-application",
      "manageColumns": [
        {
          "name": "debtorId",
          "label": "Debtor Name",
          "type": "modal",
          "request": {
            "method": "GET",
            "url": "debtor/drawer"
          }
        },
        {
          "name": "applicationId",
          "label": "Application Number",
          "type": "redirectLink"
        },
        {
          "name": "entityType",
          "label": "Entity Type",
          "type": "string"
        },
        {
          "name": "status",
          "label": "Status",
          "type": "string"
        },
        {
          "name": "creditLimit",
          "label": "Requested Amount",
          "type": "amount"
        },
        {
          "name": "acceptedAmount",
          "label": "Approved Amount",
          "type": "amount"
        },
        {
          "name": "requestDate",
          "label": "Requested Date",
          "type": "date"
        },
        {
          "name": "approvalOrDecliningDate",
          "label": "Approval Date",
          "type": "date"
        },
        {
          "name": "expiryDate",
          "label": "Expiry Date",
          "type": "date"
        },
        {
          "name": "createdById",
          "label": "Submitted By",
          "type": "string"
        },
        {
          "name": "outstandingAmount",
          "label": "Outstanding Amount",
          "type": "amount"
        },
        {
          "name": "createdAt",
          "label": "Created Date",
          "type": "date"
        },
        {
          "name": "updatedAt",
          "label": "Modified Date",
          "type": "date"
        },
        {
          "name": "comments",
          "label": "Comments",
          "type": "string"
        }
      ],
      "defaultColumns": [
        "entityType",
        "debtorId",
        "creditLimit",
        "applicationId",
        "requestDate",
        "approvalOrDecliningDate",
        "createdById",
        "comments"
      ]
    },
    {
      "name": "client-claim",
      "manageColumns": [
        {
          "name": "name",
          "label": "Claim Name",
          "type": "string"
        },
        {
          "name": "notifiedofcase",
          "label": "Notified of Case",
          "type": "date"
        },
        {
          "name": "claimsinforequested",
          "label": "Claims Info Requested",
          "type": "string"
        },
        {
          "name": "claimsinforeviewed",
          "label": "Claims Info Reviewed",
          "type": "string"
        },
        {
          "name": "datesubmittedtouw",
          "label": "Date Submitted to U/W",
          "type": "date"
        },
        {
          "name": "podreceived",
          "label": "POD Received",
          "type": "string"
        },
        {
          "name": "podsenttouw",
          "label": "POD Sent to U/W",
          "type": "date"
        },
        {
          "name": "codrequested",
          "label": "COD Requested",
          "type": "date"
        },
        {
          "name": "codreceived",
          "label": "COD Received",
          "type": "date"
        },
        {
          "name": "grossdebtamount",
          "label": "Gross Debt Amount",
          "type": "amount"
        },
        {
          "name": "amountpaid",
          "label": "Amount Paid",
          "type": "amount"
        },
        {
          "name": "receivedlolfromuw",
          "label": "Received LOL from U/W",
          "type": "date"
        },
        {
          "name": "claimpaidbyuw",
          "label": "Claim Paid by U/W",
          "type": "date"
        },
        {
          "name": "reimbursementrequired",
          "label": "Reimbursement Required",
          "type": "string"
        },
        {
          "name": "reimbursementrequested",
          "label": "Reimbursement Requested",
          "type": "string"
        },
        {
          "name": "reimbursementreceived",
          "label": "Reimbursement Received",
          "type": "date"
        },
        {
          "name": "repaymentplanamount",
          "label": "Repayment Plan Amount",
          "type": "amount"
        },
        {
          "name": "instalmentamounts",
          "label": "Instalment Amounts",
          "type": "amount"
        },
        {
          "name": "frequency",
          "label": "Frequency",
          "type": "string"
        },
        {
          "name": "repaymentplanlength",
          "label": "Repayment Plan Length",
          "type": "string"
        },
        {
          "name": "finalpaymentdate",
          "label": "Final Payment Date",
          "type": "date"
        },
        {
          "name": "tradinghistory",
          "label": "Trading History",
          "type": "string"
        },
        {
          "name": "dljustification",
          "label": "D/L Justification",
          "type": "string"
        },
        {
          "name": "underwriter",
          "label": "Insurer Name",
          "type": "string"
        },
        {
          "name": "description",
          "label": "Notes",
          "type": "string"
        },
        {
          "name": "stage",
          "label": "Stage",
          "type": "string"
        },
        {
          "name": "reimbursementspaid",
          "label": "Reimbursements Paid",
          "type": "amount"
        },
        {
          "name": "dateofoldestinvoice",
          "label": "Date of Oldest Invoice",
          "type": "date"
        },
        {
          "name": "sector",
          "label": "Sector",
          "type": "string"
        },
        {
          "name": "createddate",
          "label": "Created Date",
          "type": "date"
        }
      ],
      "defaultColumns": [
        "name",
        "stage",
        "underwriter",
        "createddate",
        "modifieddate",
        "notifiedofcase"
      ]
    },
    {
      "name": "client-policy",
      "manageColumns": [
        {
          "name": "insurerId",
          "label": "Insurer Name",
          "type": "string"
        },
        {
          "name": "product",
          "label": "Product",
          "type": "string"
        },
        {
          "name": "policyNumber",
          "label": "Policy Number",
          "type": "modal",
          "request": {
            "method": "GET",
            "url": "policy/client/policy-details"
          }
        },
        {
          "name": "policyPeriod",
          "label": "Policy Period",
          "type": "string"
        },
        {
          "name": "policyCurrency",
          "label": "Policy Currency",
          "type": "string"
        },
        {
          "name": "inceptionDate",
          "label": "Inception Date",
          "type": "date"
        },
        {
          "name": "expiryDate",
          "label": "Expiry Date",
          "type": "date"
        },
        {
          "name": "createdAt",
          "label": "Created Date",
          "type": "date"
        },
        {
          "name": "updatedAt",
          "label": "Modified Date",
          "type": "date"
        }
      ],
      "defaultColumns": [
        "insurerId",
        "product",
        "policyNumber",
        "policyPeriod",
        "policyCurrency",
        "inceptionDate",
        "expiryDate"
      ]
    },
    {
      "name": "client-task",
      "manageColumns": [
        {
          "name": "priority",
          "label": "Priority",
          "type": "string"
        },
        {
          "name": "description",
          "label": "Description",
          "type": "string"
        },
        {
          "name": "comments",
          "label": "Comments",
          "type": "string"
        },
        {
          "name": "entityType",
          "label": "Entity Type",
          "type": "string"
        },
        {
          "name": "entityId",
          "label": "Entity Name",
          "type": "modal"
        },
        {
          "name": "createdById",
          "label": "Created By",
          "type": "string"
        },
        {
          "name": "assigneeId",
          "label": "Assignee",
          "type": "string"
        },
        {
          "name": "dueDate",
          "label": "Due Date",
          "type": "date"
        },
        {
          "name": "createdAt",
          "label": "Created Date",
          "type": "date"
        },
        {
          "name": "updatedAt",
          "label": "Modified Date",
          "type": "date"
        }
      ],
      "defaultColumns": [
        "priority",
        "description",
        "comments",
        "entityId",
        "assigneeId",
        "dueDate"
      ]
    },
    {
      "name": "client-document",
      "manageColumns": [
        {
          "name": "documentTypeId",
          "label": "Document Type",
          "type": "string"
        },
        {
          "name": "description",
          "label": "Description",
          "type": "string"
        },
        {
          "name": "originalFileName",
          "label": "Link",
          "type": "link",
          "request": {
            "method": "GET",
            "url": "document/download?action=view&documentIds="
          }
        },
        {
          "name": "uploadById",
          "label": "Uploaded By",
          "type": "string"
        },
        {
          "name": "createdAt",
          "label": "Created Date",
          "type": "date"
        }
      ],
      "defaultColumns": [
        "description",
        "documentTypeId",
        "createdAt",
        "uploadById",
        "originalFileName"
      ]
    },
    {
      "name": "credit-limit",
      "manageColumns": [
        {
          "name": "entityName",
          "label": "Name",
          "type": "modal",
          "request": {
            "method": "GET",
            "url": "client/credit-limit/drawer-details"
          }
        },
        {
          "name": "entityType",
          "label": "Entity Type",
          "type": "string"
        },
        {
          "name": "activeApplicationId",
          "label": "Application Number",
          "type": "modal",
          "request": {
            "method": "GET",
            "url": "application/drawer-details"
          }
        },
        {
          "name": "creditLimit",
          "label": "Credit Limit",
          "type": "amount"
        },
        {
          "name": "limitType",
          "label": "Limit Type",
          "type": "string"
        },
        {
          "name": "approvalOrDecliningDate",
          "label": "Approval Date",
          "type": "date"
        },
        {
          "name": "expiryDate",
          "label": "Expiry Date",
          "type": "date"
        },
        {
          "name": "abn",
          "label": "ABN/NZBN",
          "type": "string"
        },
        {
          "name": "stakeHolder",
          "label": "Stakeholder",
          "type": "string"
        },
        {
          "name": "registrationNumber",
          "label": "Registration Number",
          "type": "string"
        },
        {
          "name": "acn",
          "label": "ACN/NCN",
          "type": "string"
        },
        {
          "name": "createdAt",
          "label": "Created Date",
          "type": "date"
        },
        {
          "name": "updatedAt",
          "label": "Modified Date",
          "type": "date"
        }
      ],
      "defaultColumns": [
        "entityName",
        "activeApplicationId",
        "creditLimit",
        "expiryDate",
        "createdAt"
      ]
    },
    {
      "name": "claim",
      "manageColumns": [
        {
          "name": "name",
          "label": "Claim Name",
          "type": "string"
        },
        {
          "name": "accountid",
          "label": "Client Name",
          "type": "modal",
          "request": {
            "method": "GET",
            "url": "client/details"
          }
        },
        {
          "name": "notifiedofcase",
          "label": "Notified of Case",
          "type": "date"
        },
        {
          "name": "claimsinforequested",
          "label": "Claims Info Requested",
          "type": "string"
        },
        {
          "name": "claimsinforeviewed",
          "label": "Claims Info Reviewed",
          "type": "string"
        },
        {
          "name": "datesubmittedtouw",
          "label": "Date Submitted to U/W",
          "type": "date"
        },
        {
          "name": "podreceived",
          "label": "POD Received",
          "type": "string"
        },
        {
          "name": "podsenttouw",
          "label": "POD Sent to U/W",
          "type": "date"
        },
        {
          "name": "codrequested",
          "label": "COD Requested",
          "type": "date"
        },
        {
          "name": "codreceived",
          "label": "COD Received",
          "type": "date"
        },
        {
          "name": "grossdebtamount",
          "label": "Gross Debt Amount",
          "type": "amount"
        },
        {
          "name": "amountpaid",
          "label": "Amount Paid",
          "type": "amount"
        },
        {
          "name": "receivedlolfromuw",
          "label": "Received LOL from U/W",
          "type": "date"
        },
        {
          "name": "claimpaidbyuw",
          "label": "Claim Paid by U/W",
          "type": "date"
        },
        {
          "name": "reimbursementrequired",
          "label": "Reimbursement Required",
          "type": "string"
        },
        {
          "name": "reimbursementrequested",
          "label": "Reimbursement Requested",
          "type": "string"
        },
        {
          "name": "reimbursementreceived",
          "label": "Reimbursement Received",
          "type": "date"
        },
        {
          "name": "repaymentplanamount",
          "label": "Repayment Plan Amount",
          "type": "amount"
        },
        {
          "name": "instalmentamounts",
          "label": "Instalment Amounts",
          "type": "amount"
        },
        {
          "name": "frequency",
          "label": "Frequency",
          "type": "string"
        },
        {
          "name": "repaymentplanlength",
          "label": "Repayment Plan Length",
          "type": "string"
        },
        {
          "name": "finalpaymentdate",
          "label": "Final Payment Date",
          "type": "date"
        },
        {
          "name": "tradinghistory",
          "label": "Trading History",
          "type": "string"
        },
        {
          "name": "dljustification",
          "label": "D/L Justification",
          "type": "string"
        },
        {
          "name": "underwriter",
          "label": "Insurer Name",
          "type": "string"
        },
        {
          "name": "description",
          "label": "Notes",
          "type": "string"
        },
        {
          "name": "stage",
          "label": "Stage",
          "type": "string"
        },
        {
          "name": "reimbursementspaid",
          "label": "Reimbursements Paid",
          "type": "amount"
        },
        {
          "name": "dateofoldestinvoice",
          "label": "Date of Oldest Invoice",
          "type": "date"
        },
        {
          "name": "sector",
          "label": "Sector",
          "type": "string"
        },
        {
          "name": "createddate",
          "label": "Created Date",
          "type": "date"
        }
      ],
      "defaultColumns": [
        "name",
        "accountid",
        "stage",
        "underwriter",
        "createddate",
        "modifieddate",
        "notifiedofcase"
      ]
    },
    {
      "name": "debtor",
      "manageColumns": [
        {
          "name": "debtorCode",
          "label": "Debtor Code",
          "type": "string"
        },
        {
          "name": "status",
          "label": "Status",
          "type": "string"
        },
        {
          "name": "entityName",
          "label": "Entity Name",
          "type": "string"
        },
        {
          "name": "abn",
          "label": "ABN/NZBN",
          "type": "string"
        },
        {
          "name": "acn",
          "label": "ACN/NCN",
          "type": "string"
        },
        {
          "name": "registrationNumber",
          "label": "Registration Number",
          "type": "string"
        },
        {
          "name": "tradingName",
          "label": "Trading Name",
          "type": "string"
        },
        {
          "name": "entityType",
          "label": "Entity Type",
          "type": "string"
        },
        {
          "name": "fullAddress",
          "label": "Full Address",
          "type": "string"
        },
        {
          "name": "property",
          "label": "Property",
          "type": "string"
        },
        {
          "name": "unitNumber",
          "label": "Unit Number",
          "type": "string"
        },
        {
          "name": "streetNumber",
          "label": "Street Number",
          "type": "string"
        },
        {
          "name": "streetName",
          "label": "Street Name",
          "type": "string"
        },
        {
          "name": "streetType",
          "label": "Street Type",
          "type": "string"
        },
        {
          "name": "suburb",
          "label": "Suburb",
          "type": "string"
        },
        {
          "name": "state",
          "label": "Country/State",
          "type": "string"
        },
        {
          "name": "country",
          "label": "Country",
          "type": "string"
        },
        {
          "name": "postCode",
          "label": "Postcode/Zip",
          "type": "string"
        },
        {
          "name": "contactNumber",
          "label": "Contact Number",
          "type": "string"
        },
        {
          "name": "riskRating",
          "label": "Risk Rating",
          "type": "string"
        },
        {
          "name": "reviewDate",
          "label": "Review Date",
          "type": "date"
        },
        {
          "name": "isActive",
          "label": "Active",
          "type": "string"
        },
        {
          "name": "createdAt",
          "label": "Created Date",
          "type": "date"
        },
        {
          "name": "updatedAt",
          "label": "Modified Date",
          "type": "date"
        }
      ],
      "defaultColumns": [
        "debtorCode",
        "status",
        "abn",
        "entityName",
        "acn",
        "entityType",
        "registrationNumber",
        "riskRating",
        "reviewDate",
        "country"
      ]
    },
    {
      "name": "debtor-application",
      "manageColumns": [
        {
          "name": "clientId",
          "label": "Client Name",
          "type": "modal",
          "request": {
            "method": "GET",
            "url": "client/details"
          }
        },
        {
          "name": "applicationId",
          "label": "Application Number",
          "type": "redirectLink"
        },
        {
          "name": "status",
          "label": "Status",
          "type": "string"
        },
        {
          "name": "creditLimit",
          "label": "Requested Amount",
          "type": "amount"
        },
        {
          "name": "acceptedAmount",
          "label": "Approved Amount",
          "type": "amount"
        },
        {
          "name": "requestDate",
          "label": "Requested Date",
          "type": "date"
        },
        {
          "name": "approvalOrDecliningDate",
          "label": "Approval Date",
          "type": "date"
        },
        {
          "name": "expiryDate",
          "label": "Expiry Date",
          "type": "date"
        },
        {
          "name": "createdById",
          "label": "Submitted By",
          "type": "string"
        },
        {
          "name": "outstandingAmount",
          "label": "Outstanding Amount",
          "type": "amount"
        },
        {
          "name": "createdAt",
          "label": "Created Date",
          "type": "date"
        },
        {
          "name": "updatedAt",
          "label": "Modified Date",
          "type": "date"
        },
        {
          "name": "comments",
          "label": "Comments",
          "type": "string"
        }
      ],
      "defaultColumns": [
        "clientId",
        "applicationId",
        "creditLimit",
        "status",
        "requestDate",
        "approvalOrDecliningDate",
        "acceptedAmount",
        "comments"
      ]
    },
    {
      "name": "debtor-task",
      "manageColumns": [
        {
          "name": "priority",
          "label": "Priority",
          "type": "string"
        },
        {
          "name": "description",
          "label": "Description",
          "type": "string"
        },
        {
          "name": "comments",
          "label": "Comments",
          "type": "string"
        },
        {
          "name": "entityType",
          "label": "Entity Type",
          "type": "string"
        },
        {
          "name": "entityId",
          "label": "Entity Name",
          "type": "modal"
        },
        {
          "name": "createdById",
          "label": "Created By",
          "type": "string"
        },
        {
          "name": "assigneeId",
          "label": "Assignee",
          "type": "string"
        },
        {
          "name": "dueDate",
          "label": "Due Date",
          "type": "date"
        },
        {
          "name": "createdAt",
          "label": "Created Date",
          "type": "date"
        },
        {
          "name": "updatedAt",
          "label": "Modified Date",
          "type": "date"
        }
      ],
      "defaultColumns": [
        "priority",
        "description",
        "comments",
        "entityId",
        "assigneeId",
        "dueDate"
      ]
    },
    {
      "name": "debtor-document",
      "manageColumns": [
        {
          "name": "documentTypeId",
          "label": "Document Type",
          "type": "string"
        },
        {
          "name": "description",
          "label": "Description",
          "type": "string"
        },
        {
          "name": "originalFileName",
          "label": "Link",
          "type": "link",
          "request": {
            "method": "GET",
            "url": "document/download?action=view&documentIds="
          }
        },
        {
          "name": "uploadById",
          "label": "Uploaded By",
          "type": "string"
        },
        {
          "name": "createdAt",
          "label": "Created Date",
          "type": "date"
        }
      ],
      "defaultColumns": [
        "description",
        "documentTypeId",
        "originalFileName",
        "uploadById",
        "createdAt"
      ]
    },
    {
      "name": "debtor-credit-limit",
      "manageColumns": [
        {
          "name": "name",
          "label": "Client Name",
          "type": "modal",
          "request": {
            "method": "GET",
            "url": "client/details"
          }
        },
        {
          "name": "contactNumber",
          "label": "Contact Number",
          "type": "string"
        },
        {
          "name": "activeApplicationId",
          "label": "Application Number",
          "type": "modal",
          "request": {
            "method": "GET",
            "url": "application/drawer-details"
          }
        },
        {
          "name": "creditLimit",
          "label": "Credit Limit",
          "type": "amount"
        },
        {
          "name": "limitType",
          "label": "Limit Type",
          "type": "string"
        },
        {
          "name": "approvalOrDecliningDate",
          "label": "Approval Date",
          "type": "date"
        },
        {
          "name": "expiryDate",
          "label": "Expiry Date",
          "type": "date"
        },
        {
          "name": "abn",
          "label": "ABN",
          "type": "string"
        },
        {
          "name": "acn",
          "label": "ACN",
          "type": "string"
        },
        {
          "name": "createdAt",
          "label": "Created Date",
          "type": "date"
        },
        {
          "name": "updatedAt",
          "label": "Modified Date",
          "type": "date"
        }
      ],
      "defaultColumns": [
        "name",
        "activeApplicationId",
        "creditLimit",
        "expiryDate",
        "createdAt"
      ]
    },
    {
      "name": "insurer",
      "manageColumns": [
        {
          "name": "name",
          "label": "Name",
          "type": "string"
        },
        {
          "name": "contactNumber",
          "label": "Contact Number",
          "type": "string"
        },
        {
          "name": "fullAddress",
          "label": "Full Address",
          "type": "string"
        },
        {
          "name": "addressLine",
          "label": "Address Line",
          "type": "string"
        },
        {
          "name": "city",
          "label": "City",
          "type": "string"
        },
        {
          "name": "state",
          "label": "Country/State",
          "type": "string"
        },
        {
          "name": "country",
          "label": "Country",
          "type": "string"
        },
        {
          "name": "zipCode",
          "label": "Postcode/Zip",
          "type": "string"
        },
        {
          "name": "website",
          "label": "Website",
          "type": "string"
        },
        {
          "name": "createdAt",
          "label": "Created Date",
          "type": "date"
        },
        {
          "name": "updatedAt",
          "label": "Modified Date",
          "type": "date"
        }
      ],
      "defaultColumns": [
        "name",
        "contactNumber",
        "fullAddress",
        "website",
        "createdAt",
        "updatedAt"
      ]
    },
    {
      "name": "insurer-user",
      "manageColumns": [
        {
          "name": "name",
          "label": "Name",
          "type": "modal",
          "request": {
            "method": "GET",
            "url": "insurer/user-details"
          }
        },
        {
          "name": "email",
          "label": "Email",
          "type": "string"
        },
        {
          "name": "contactNumber",
          "label": "Contact Number",
          "type": "string"
        },
        {
          "name": "direct",
          "label": "Direct",
          "type": "string"
        },
        {
          "name": "jobTitle",
          "label": "Job Title",
          "type": "string"
        },
        {
          "name": "hasLeftCompany",
          "label": "Left Company",
          "type": "string"
        },
        {
          "name": "isDecisionMaker",
          "label": "Decision Maker",
          "type": "string"
        },
        {
          "name": "createdAt",
          "label": "Created Date",
          "type": "date"
        },
        {
          "name": "updatedAt",
          "label": "Modified Date",
          "type": "date"
        }
      ],
      "defaultColumns": [
        "name",
        "email",
        "jobTitle",
        "direct",
        "contactNumber",
        "updatedAt"
      ]
    },
    {
      "name": "insurer-policy",
      "manageColumns": [
        {
          "name": "product",
          "label": "Product",
          "type": "string"
        },
        {
          "name": "policyNumber",
          "label": "Policy Number",
          "type": "modal",
          "request": {
            "method": "GET",
            "url": "policy/details"
          }
        },
        {
          "name": "policyPeriod",
          "label": "Policy Period",
          "type": "string"
        },
        {
          "name": "clientId",
          "label": "Client Name",
          "type": "string"
        },
        {
          "name": "policyCurrency",
          "label": "Policy Currency",
          "type": "string"
        },
        {
          "name": "inceptionDate",
          "label": "Inception Date",
          "type": "date"
        },
        {
          "name": "expiryDate",
          "label": "Expiry Date",
          "type": "date"
        },
        {
          "name": "createdAt",
          "label": "Created Date",
          "type": "date"
        },
        {
          "name": "updatedAt",
          "label": "Modified Date",
          "type": "date"
        }
      ],
      "defaultColumns": [
        "clientId",
        "product",
        "policyNumber",
        "policyPeriod",
        "policyCurrency",
        "inceptionDate",
        "expiryDate"
      ]
    },
    {
      "name": "client-list-report",
      "manageColumns": [
        {
          "name": "name",
          "label": "Client Name",
          "type": "string"
        },
        {
          "name": "discretionaryLimit",
          "label": "Discretionary Limit",
          "type": "amount"
        },
        {
          "name": "insurerId",
          "label": "Insurer Name",
          "type": "string"
        },
        {
          "name": "creditChecks",
          "label": "No of Credit Checks",
          "type": "number"
        },
        {
          "name": "contactNumber",
          "label": "Contact Number",
          "type": "string"
        },
        {
          "name": "riskAnalystId",
          "label": "Risk Analyst",
          "type": "string"
        },
        {
          "name": "serviceManagerId",
          "label": "Service Manager",
          "type": "string"
        },
        {
          "name": "sector",
          "label": "Sector",
          "type": "string"
        },
        {
          "name": "salesPerson",
          "label": "Sales Person",
          "type": "string"
        },
        {
          "name": "inceptionDate",
          "label": "Inception Date",
          "type": "date"
        },
        {
          "name": "expiryDate",
          "label": "Expiry Date",
          "type": "date"
        },
        {
          "name": "totalApplication",
          "label": "Total Application",
          "type": "string"
        },
        {
          "name": "remainingApplication",
          "label": "Remaining Application",
          "type": "string"
        }
      ],
      "defaultColumns": [
        "name",
        "discretionaryLimit",
        "insurerId",
        "creditChecks",
        "riskAnalystId",
        "serviceManagerId"
      ]
    },
    {
      "name": "limit-list-report",
      "manageColumns": [
        {
          "name": "clientId",
          "label": "Client Name",
          "type": "string"
        },
        {
          "name": "insurerId",
          "label": "Insurer Name",
          "type": "string"
        },
        {
          "name": "debtorId",
          "label": "Debtor Name",
          "type": "string"
        },
        {
          "name": "stakeHolder",
          "label": "Stakeholder",
          "type": "string"
        },
        {
          "name": "abn",
          "label": "ABN/NZBN",
          "type": "string"
        },
        {
          "name": "acn",
          "label": "ACN/NCN",
          "type": "string"
        },
        {
          "name": "registrationNumber",
          "label": "Registration Number",
          "type": "string"
        },
        {
          "name": "country",
          "label": "Country",
          "type": "string"
        },
        {
          "name": "applicationId",
          "label": "Application Number",
          "type": "string"
        },
        {
          "name": "creditLimit",
          "label": "Requested Amount",
          "type": "amount"
        },
        {
          "name": "acceptedAmount",
          "label": "Approved Amount",
          "type": "amount"
        },
        {
          "name": "approvalOrDecliningDate",
          "label": "Approval Date",
          "type": "date"
        },
        {
          "name": "expiryDate",
          "label": "Expiry Date",
          "type": "date"
        },
        {
          "name": "limitType",
          "label": "Limit Type",
          "type": "string"
        },
        {
          "name": "clientReference",
          "label": "Client Reference",
          "type": "string"
        },
        {
          "name": "comments",
          "label": "Comments",
          "type": "string"
        }
      ],
      "defaultColumns": [
        "clientId",
        "insurerId",
        "debtorId",
        "abn",
        "registrationNumber",
        "country",
        "applicationId"
      ]
    },
    {
      "name": "pending-application-report",
      "manageColumns": [
        {
          "name": "clientId",
          "label": "Client Name",
          "type": "string"
        },
        {
          "name": "debtorId",
          "label": "Debtor Name",
          "type": "string"
        },
        {
          "name": "entityType",
          "label": "Debtor Entity Type",
          "type": "string"
        },
        {
          "name": "applicationId",
          "label": "Application Number",
          "type": "string"
        },
        {
          "name": "status",
          "label": "Application Status",
          "type": "string"
        },
        {
          "name": "insurerId",
          "label": "Insurer Name",
          "type": "string"
        },
        {
          "name": "creditLimit",
          "label": "Requested Amount",
          "type": "amount"
        },
        {
          "name": "limitType",
          "label": "Limit Type",
          "type": "string"
        },
        {
          "name": "requestDate",
          "label": "Applied Date",
          "type": "date"
        }
      ],
      "defaultColumns": [
        "clientId",
        "insurerId",
        "debtorId",
        "abn",
        "registrationNumber",
        "country",
        "applicationId"
      ]
    },
    {
      "name": "review-report",
      "manageColumns": [
        {
          "name": "clientId",
          "label": "Client Name",
          "type": "string"
        },
        {
          "name": "entityName",
          "label": "Entity Name",
          "type": "string"
        },
        {
          "name": "abn",
          "label": "ABN/NZBN",
          "type": "string"
        },
        {
          "name": "acn",
          "label": "ACN/NCN",
          "type": "string"
        },
        {
          "name": "registrationNumber",
          "label": "Registration Number",
          "type": "string"
        },
        {
          "name": "tradingName",
          "label": "Trading Name",
          "type": "string"
        },
        {
          "name": "insurerId",
          "label": "Insurer Name",
          "type": "string"
        },
        {
          "name": "entityType",
          "label": "Entity Type",
          "type": "string"
        },
        {
          "name": "reviewDate",
          "label": "Review Date",
          "type": "date"
        },
        {
          "name": "fullAddress",
          "label": "Full Address",
          "type": "string"
        },
        {
          "name": "property",
          "label": "Property",
          "type": "string"
        },
        {
          "name": "unitNumber",
          "label": "Unit Number",
          "type": "string"
        },
        {
          "name": "streetNumber",
          "label": "Street Number",
          "type": "string"
        },
        {
          "name": "streetName",
          "label": "Street Name",
          "type": "string"
        },
        {
          "name": "streetType",
          "label": "Street Type",
          "type": "string"
        },
        {
          "name": "suburb",
          "label": "Suburb",
          "type": "string"
        },
        {
          "name": "state",
          "label": "Country/State",
          "type": "string"
        },
        {
          "name": "country",
          "label": "Country",
          "type": "string"
        },
        {
          "name": "postCode",
          "label": "Postcode/Zip",
          "type": "string"
        },
        {
          "name": "contactNumber",
          "label": "Contact Number",
          "type": "string"
        },
        {
          "name": "riskRating",
          "label": "Risk Rating",
          "type": "string"
        },
        {
          "name": "updatedAt",
          "label": "Modified Date",
          "type": "date"
        }
      ],
      "defaultColumns": [
        "clientId",
        "abn",
        "entityName",
        "acn",
        "entityType",
        "registrationNumber",
        "riskRating",
        "reviewDate",
        "country"
      ]
    },
    {
      "name": "usage-report",
      "manageColumns": [
        {
          "name": "name",
          "label": "Client Name",
          "type": "string"
        },
        {
          "name": "insurerId",
          "label": "Insurer Name",
          "type": "string"
        },
        {
          "name": "creditChecks",
          "label": "Credit Checks Purchased",
          "type": "number"
        },
        {
          "name": "creditChecksUsed",
          "label": "Credit Checks Used",
          "type": "number"
        },
        {
          "name": "nzCreditChecks",
          "label": "Credit Checks NZ Purchased",
          "type": "number"
        },
        {
          "name": "nzCreditChecksUsed",
          "label": "Credit Checks NZ Used",
          "type": "number"
        },
        {
          "name": "healthChecks",
          "label": "Health Checks Purchased",
          "type": "number"
        },
        {
          "name": "healthChecksUsed",
          "label": "Health Checks Used",
          "type": "number"
        },
        {
          "name": "alerts247",
          "label": "24/7 Alerts Purchased",
          "type": "number"
        },
        {
          "name": "alerts247Used",
          "label": "24/7 Alerts Used",
          "type": "number"
        },
        {
          "name": "policyNumber",
          "label": "Current Policy Number",
          "type": "string"
        },
        {
          "name": "inceptionDate",
          "label": "Policy Inception Date",
          "type": "date"
        },
        {
          "name": "expiryDate",
          "label": "Policy Expiry Date",
          "type": "date"
        },
        {
          "name": "riskAnalystId",
          "label": "Risk Analyst",
          "type": "string"
        },
        {
          "name": "serviceManagerId",
          "label": "Service Manager",
          "type": "string"
        }
      ],
      "defaultColumns": [
        "clientId",
        "insurerId",
        "creditChecks",
        "noOfCreditChecksUsed",
        "policyNumber",
        "inceptionDate",
        "expiryDate"
      ]
    },
    {
      "name": "usage-per-client-report",
      "manageColumns": [
        {
          "name": "clientId",
          "label": "Client Name",
          "type": "string"
        },
        {
          "name": "insurerId",
          "label": "Insurer Name",
          "type": "string"
        },
        {
          "name": "debtorId",
          "label": "Debtor Name",
          "type": "string"
        },
        {
          "name": "entityType",
          "label": "Debtor Entity Type",
          "type": "string"
        },
        {
          "name": "abn",
          "label": "Debtor ABN/NZBN",
          "type": "string"
        },
        {
          "name": "acn",
          "label": "Debtor ACN/NCN",
          "type": "string"
        },
        {
          "name": "registrationNumber",
          "label": "Debtor Registration Number",
          "type": "string"
        },
        {
          "name": "country",
          "label": "Debtor Country",
          "type": "string"
        },
        {
          "name": "creditLimitStatus",
          "label": "Current Status of Credit Limit",
          "type": "string"
        },
        {
          "name": "creditLimit",
          "label": "Credit Limit",
          "type": "amount"
        },
        {
          "name": "applicationCount",
          "label": "Application Count",
          "type": "string"
        },
        {
          "name": "applicationId",
          "label": "Application Number",
          "type": "string"
        },
        {
          "name": "status",
          "label": "Application Status",
          "type": "string"
        },
        {
          "name": "requestedAmount",
          "label": "Requested Amount",
          "type": "amount"
        },
        {
          "name": "acceptedAmount",
          "label": "Approved Amount",
          "type": "amount"
        },
        {
          "name": "approvalOrDecliningDate",
          "label": "Approval Date",
          "type": "date"
        },
        {
          "name": "expiryDate",
          "label": "Expiry Date",
          "type": "date"
        },
        {
          "name": "limitType",
          "label": "Limit Type",
          "type": "string"
        },
        {
          "name": "clientReference",
          "label": "Client Reference",
          "type": "string"
        },
        {
          "name": "comments",
          "label": "Comments",
          "type": "string"
        }
      ],
      "defaultColumns": [
        "clientId",
        "insurerId",
        "debtorId",
        "entityType",
        "abn",
        "registrationNumber",
        "creditLimitStatus",
        "creditLimit"
      ]
    },
    {
      "name": "limit-history-report",
      "manageColumns": [
        {
          "name": "applicationId",
          "label": "Application Number",
          "type": "string"
        },
        {
          "name": "status",
          "label": "Application Status",
          "type": "string"
        },
        {
          "name": "clientId",
          "label": "Client Name",
          "type": "string"
        },
        {
          "name": "debtorId",
          "label": "Debtor Name",
          "type": "string"
        },
        {
          "name": "entityType",
          "label": "Debtor Entity Type",
          "type": "string"
        },
        {
          "name": "abn",
          "label": "Debtor ABN/NZBN",
          "type": "string"
        },
        {
          "name": "acn",
          "label": "Debtor ACN/NCN",
          "type": "string"
        },
        {
          "name": "registrationNumber",
          "label": "Debtor Registration Number",
          "type": "string"
        },
        {
          "name": "country",
          "label": "Debtor Country",
          "type": "string"
        },
        {
          "name": "insurerId",
          "label": "Insurer Name",
          "type": "string"
        },
        {
          "name": "creditLimit",
          "label": "Requested Amount",
          "type": "amount"
        },
        {
          "name": "acceptedAmount",
          "label": "Approved Amount",
          "type": "amount"
        },
        {
          "name": "approvalOrDecliningDate",
          "label": "Approval Date",
          "type": "date"
        },
        {
          "name": "expiryDate",
          "label": "Expiry Date",
          "type": "date"
        },
        {
          "name": "limitType",
          "label": "Limit Type",
          "type": "string"
        },
        {
          "name": "clientReference",
          "label": "Client Reference",
          "type": "string"
        },
        {
          "name": "comments",
          "label": "Comments",
          "type": "string"
        }
      ],
      "defaultColumns": [
        "clientId",
        "insurerId",
        "debtorId",
        "abn",
        "registrationNumber",
        "country",
        "applicationId",
        "acceptedAmount",
        "approvalOrDecliningDate",
        "expiryDate"
      ]
    },
    {
      "name": "claims-report",
      "manageColumns": [
        {
          "name": "name",
          "label": "Claim Name",
          "type": "string"
        },
        {
          "name": "accountid",
          "label": "Client Name",
          "type": "string"
        },
        {
          "name": "notifiedofcase",
          "label": "Notified of Case",
          "type": "date"
        },
        {
          "name": "claimsinforequested",
          "label": "Claims Info Requested",
          "type": "string"
        },
        {
          "name": "claimsinforeviewed",
          "label": "Claims Info Reviewed",
          "type": "string"
        },
        {
          "name": "datesubmittedtouw",
          "label": "Date Submitted to U/W",
          "type": "string"
        },
        {
          "name": "podreceived",
          "label": "POD Received",
          "type": "string"
        },
        {
          "name": "podsenttouw",
          "label": "POD Sent to U/W",
          "type": "string"
        },
        {
          "name": "codrequested",
          "label": "COD Requested",
          "type": "string"
        },
        {
          "name": "codreceived",
          "label": "COD Received",
          "type": "string"
        },
        {
          "name": "grossdebtamount",
          "label": "Gross Debt Amount",
          "type": "string"
        },
        {
          "name": "amountpaid",
          "label": "Amount Paid",
          "type": "string"
        },
        {
          "name": "receivedlolfromuw",
          "label": "Received LOL from U/W",
          "type": "string"
        },
        {
          "name": "claimpaidbyuw",
          "label": "Claim Paid by U/W",
          "type": "string"
        },
        {
          "name": "reimbursementrequired",
          "label": "Reimbursement Required",
          "type": "string"
        },
        {
          "name": "reimbursementrequested",
          "label": "Reimbursement Requested",
          "type": "string"
        },
        {
          "name": "reimbursementreceived",
          "label": "Reimbursement Received",
          "type": "string"
        },
        {
          "name": "tradinghistory",
          "label": "Trading History",
          "type": "string"
        },
        {
          "name": "repaymentplanamount",
          "label": "Repayment Plan Amount",
          "type": "string"
        },
        {
          "name": "instalmentamounts",
          "label": "Instalment Amounts",
          "type": "string"
        },
        {
          "name": "frequency",
          "label": "Frequency",
          "type": "string"
        },
        {
          "name": "repaymentplanlength",
          "label": "Repayment Plan Length",
          "type": "string"
        },
        {
          "name": "finalpaymentdate",
          "label": "Final Payment Date",
          "type": "string"
        },
        {
          "name": "dljustification",
          "label": "D/L Justification",
          "type": "string"
        },
        {
          "name": "stage",
          "label": "Stage",
          "type": "string"
        },
        {
          "name": "reimbursementspaid",
          "label": "Reimbursements Paid",
          "type": "string"
        },
        {
          "name": "dateofoldestinvoice",
          "label": "Date of Oldest Invoice",
          "type": "string"
        },
        {
          "name": "underwriter",
          "label": "Underwriter",
          "type": "string"
        },
        {
          "name": "description",
          "label": "Notes",
          "type": "string"
        },
        {
          "name": "sector",
          "label": "Sector",
          "type": "string"
        }
      ],
      "defaultColumns": [
        "name",
        "accountid",
        "claimsinforequested",
        "claimsinforeviewed",
        "datesubmittedtouw",
        "reimbursementrequired",
        "reimbursementrequested",
        "reimbursementreceived",
        "stage"
      ]
    },
    {
      "name": "alerts",
      "manageColumns": [
        {
          "name": "clientName",
          "label": "Client Name",
          "type": "string"
        },
        {
          "name": "debtorName",
          "label": "Debtor name",
          "type": "string"
        },
        {
          "name": "abn",
          "label": "ABN/NZBN",
          "type": "string"
        },
        {
          "name": "acn",
          "label": "ACN/NCN",
          "type": "string"
        },
        {
          "name": "alertCategory",
          "label": "Alert Category",
          "type": "string"
        },
        {
          "name": "alertType",
          "label": "Alert Type",
          "type": "string"
        },
        {
          "name": "alertDate",
          "label": "Alert Date",
          "type": "date"
        },
        {
          "name": "alertPriority",
          "label": "Alert Priority",
          "type": "string"
        },
        {
          "name": "description",
          "label": "Description",
          "type": "string"
        },
        {
          "name": "status",
          "label": "Status",
          "type": "string"
        }
      ],
      "defaultColumns": [
        "clientName",
        "debtorName",
        "alertCategory",
        "alertType",
        "alertPriority",
        "alertDate"
      ]
    },
    {
      "name": "alert-report",
      "manageColumns": [
        {
          "name": "clientName",
          "label": "Client Name",
          "type": "string"
        },
        {
          "name": "debtorName",
          "label": "Debtor name",
          "type": "string"
        },
        {
          "name": "abn",
          "label": "ABN/NZBN",
          "type": "string"
        },
        {
          "name": "acn",
          "label": "ACN/NCN",
          "type": "string"
        },
        {
          "name": "alertCategory",
          "label": "Alert Category",
          "type": "string"
        },
        {
          "name": "alertType",
          "label": "Alert Type",
          "type": "string"
        },
        {
          "name": "alertDate",
          "label": "Alert Date",
          "type": "date"
        },
        {
          "name": "alertPriority",
          "label": "Alert Priority",
          "type": "string"
        },
        {
          "name": "description",
          "label": "Description",
          "type": "string"
        }
      ],
      "defaultColumns": [
        "clientName",
        "debtorName",
        "alertCategory",
        "alertType",
        "alertPriority",
        "alertDate"
      ]
    },
    {
      "name": "stakeholder",
      "manageColumns": [
        {
          "name": "title",
          "label": "Title",
          "type": "string"
        },
        {
          "name": "name",
          "label": "Name",
          "type": "modal",
          "request": {
            "method": "GET",
            "url": "debtor/stakeholder/drawer-details"
          }
        },
        {
          "name": "abn",
          "label": "ABN/NZBN",
          "type": "string"
        },
        {
          "name": "acn",
          "label": "ACN/NCN",
          "type": "string"
        },
        {
          "name": "registrationNumber",
          "label": "Registration Number",
          "type": "string"
        },
        {
          "name": "tradingName",
          "label": "Trading Name",
          "type": "string"
        },
        {
          "name": "entityType",
          "label": "Entity Type",
          "type": "string"
        },
        {
          "name": "dateOfBirth",
          "label": "Date Of Birth",
          "type": "date"
        },
        {
          "name": "driverLicenceNumber",
          "label": "Driver Licence Number",
          "type": "string"
        },
        {
          "name": "email",
          "label": "Email",
          "type": "string"
        },
        {
          "name": "phoneNumber",
          "label": "Phone Number",
          "type": "string"
        },
        {
          "name": "mobileNumber",
          "label": "Mobile Number",
          "type": "string"
        },
        {
          "name": "fullAddress",
          "label": "Full Address",
          "type": "string"
        },
        {
          "name": "property",
          "label": "Property",
          "type": "string"
        },
        {
          "name": "unitNumber",
          "label": "Unit Number",
          "type": "string"
        },
        {
          "name": "streetNumber",
          "label": "Street Number",
          "type": "string"
        },
        {
          "name": "streetName",
          "label": "Street Name",
          "type": "string"
        },
        {
          "name": "streetType",
          "label": "Street Type",
          "type": "string"
        },
        {
          "name": "suburb",
          "label": "Suburb",
          "type": "string"
        },
        {
          "name": "state",
          "label": "Country/State",
          "type": "string"
        },
        {
          "name": "country",
          "label": "Country",
          "type": "string"
        },
        {
          "name": "postCode",
          "label": "Postcode/Zip",
          "type": "string"
        },
        {
          "name": "allowToCheckCreditHistory",
          "label": "Allow To Check CreditHistory",
          "type": "string"
        },
        {
          "name": "createdAt",
          "label": "Created Date",
          "type": "date"
        },
        {
          "name": "updatedAt",
          "label": "Modified Date",
          "type": "date"
        }
      ],
      "defaultColumns": [
        "title",
        "name",
        "abn",
        "acn",
        "registrationNumber",
        "dateOfBirth",
        "entityType",
        "driverLicenceNumber"
      ]
    },
    {
      "name": "task",
      "manageColumns": [
        {
          "name": "priority",
          "label": "Priority",
          "type": "string"
        },
        {
          "name": "description",
          "label": "Description",
          "type": "string"
        },
        {
          "name": "comments",
          "label": "Comments",
          "type": "string"
        },
        {
          "name": "entityType",
          "label": "Entity Type",
          "type": "string"
        },
        {
          "name": "entityId",
          "label": "Entity Name",
          "type": "modal"
        },
        {
          "name": "createdById",
          "label": "Created By",
          "type": "string"
        },
        {
          "name": "assigneeId",
          "label": "Assignee",
          "type": "string"
        },
        {
          "name": "dueDate",
          "label": "Due Date",
          "type": "date"
        },
        {
          "name": "createdAt",
          "label": "Created Date",
          "type": "date"
        },
        {
          "name": "updatedAt",
          "label": "Modified Date",
          "type": "date"
        }
      ],
      "defaultColumns": [
        "priority",
        "description",
        "comments",
        "entityType",
        "assigneeId",
        "dueDate"
      ]
    },
    {
      "name": "user",
      "manageColumns": [
        {
          "name": "name",
          "label": "Name",
          "type": "string"
        },
        {
          "name": "email",
          "label": "Email",
          "type": "string"
        },
        {
          "name": "contactNumber",
          "label": "Contact Number",
          "type": "string"
        },
        {
          "name": "role",
          "label": "Role",
          "type": "string"
        },
        {
          "name": "maxCreditLimit",
          "label": "Max Credit Limit",
          "type": "amount"
        },
        {
          "name": "status",
          "label": "Status",
          "type": "string"
        },
        {
          "name": "createdAt",
          "label": "Created Date",
          "type": "date"
        },
        {
          "name": "updatedAt",
          "label": "Modified Date",
          "type": "date"
        }
      ],
      "defaultColumns": [
        "name",
        "email",
        "contactNumber",
        "role",
        "maxCreditLimit",
        "updatedAt"
      ]
    },
    {
      "name": "credit-report",
      "manageColumns": [
        {
          "name": "reportProvider",
          "label": "Report By",
          "type": "string"
        },
        {
          "name": "name",
          "label": "Name",
          "type": "string"
        },
        {
          "name": "productCode",
          "label": "Product Code",
          "type": "string"
        },
        {
          "name": "isExpired",
          "label": "Is Expired",
          "type": "boolean",
          "isDisabled": false,
          "request": {
            "method": "PUT",
            "url": "credit-report"
          }
        },
        {
          "name": "expiryDate",
          "label": "Expiry Date",
          "type": "date"
        },
        {
          "name": "createdAt",
          "label": "Generation Date",
          "type": "date"
        },
        {
          "name": "updatedAt",
          "label": "Modified Date",
          "type": "date"
        }
      ],
      "defaultColumns": [
        "name",
        "reportProvider",
        "isExpired",
        "expiryDate",
        "createdAt"
      ]
    },
    {
      "name": "import-application",
      "manageColumns": [
        {
          "name": "clientCode",
          "label": "Client Code",
          "type": "string"
        },
        {
          "name": "debtorCode",
          "label": "Debtor Code",
          "type": "string"
        },
        {
          "name": "abn",
          "label": "Debtor ABN",
          "type": "string"
        },
        {
          "name": "acn",
          "label": "Debtor ACN",
          "type": "string"
        },
        {
          "name": "companyRegistrationNumber",
          "label": "Company Registration Number",
          "type": "string"
        },
        {
          "name": "entityName",
          "label": "Debtor Entity Name",
          "type": "string"
        },
        {
          "name": "creditLimit",
          "label": "Credit Limit",
          "type": "amount"
        },
        {
          "name": "reason",
          "label": "Reason",
          "type": "string"
        }
      ]
    }
  ]
}
