{
  "modules": [
    {
      "name": "audit-logs",
      "manageColumns": [{"name": "entityType","label": "Module","type": "string"},{"name": "logDescription","label": "Log Description","type": "string"},{"name": "userType","label": "User Type","type": "string"},{"name": "userRefId","label": "User Id","type": "string"},{"name": "entityRefId","label": "Module Id","type": "string"},{"name": "actionType","label": "Action Type","type": "string"},{"name": "createdAt","label": "Created Date","type": "date"},{"name": "updatedAt","label": "Modified Date","type": "date"}],
      "defaultColumns": ["entityType", "logDescription", "userType"]
    },
    {
      "name": "application",
      "manageColumns": ["clientId","debtorId","updatedAt", "createdAt"],
      "defaultColumns": ["debtorId"]
    },
    {
      "name": "client",
      "manageColumns": ["name", "riskAnalystId", "serviceManagerId","insurerId", "crmClientId", "address.addressLine", "address.city", "address.state","address.country","address.zipCode", "crmNote", "contactNumber","website", "abn","acn", "sector","salesPerson","updatedAt","createdAt"],
      "defaultColumns": ["name","contactNumber","website", "abn","acn"]
    },
    {
      "name": "client-user",
      "manageColumns": ["clientId","firstName","lastName","contactNumber", "department", "hasPortalAccess", "hasLeftCompany", "isDecisionMaker", "crmContactId","email", "profilePicture","manageColumns","updatedAt", "createdAt"],
      "defaultColumns": ["firstName","lastName","contactNumber", "department"]
    },
    {
      "name": "client-policy",
      "manageColumns": [{"name": "insurerId","label": "Insurer Id","type": "string"},{"name": "clientId","label": "Client Id","type": "string"},{"name": "product","label": "Product","type": "string"},{"name": "policyPeriod","label": "Policy Period","type": "string"},{"name": "policyCurrency","label": "Policy Currency","type": "string"},{"name": "inceptionDate","label": "Inception Date","type": "date"},{"name": "expiryDate","label": "Expiry Date","type": "date"},{"name": "createdAt","label": "Created Date","type": "date"},{"name": "updatedAt","label": "Modified Date","type": "date"}],
      "defaultColumns": ["insurerId", "clientId", "product"]
    },
    {
      "name": "credit-limit",
      "manageColumns": ["clientId", "debtorId","creditLimit","updatedAt","createdAt"],
      "defaultColumns": ["clientId", "debtorId","creditLimit"]
    },
    {
      "name": "claim",
      "manageColumns": ["clientId", "debtorId", "applicationId", "updatedAt", "createdAt"],
      "defaultColumns": ["clientId", "debtorId", "applicationId"]
    },
    {
      "name": "debtor",
      "manageColumns": ["clientId", "debtorId","creditLimit","updatedAt","createdAt"],
      "defaultColumns": ["clientId", "debtorId","creditLimit"]
    },
    {
      "name": "document",
      "manageColumns": [{"name": "documentTypeId","label": "Document Type","type": "string"},{"name": "description","label": "Description","type": "string"},{"name": "fileName","label": "File Name","type": "string"},{"name": "uploadById","label": "Upload By","type": "string"},{"name": "entityType","label": "Entity Type","type": "string"},{"name": "entityRefId","label": "Entity Ref","type": "string"},{"name": "createdAt","label": "Created Date","type": "date"},{"name": "updatedAt","label": "Modified Date","type": "date"}],
      "defaultColumns": ["description", "fileName", "updatedAt"]
    },
    {
      "name": "insurer",
      "manageColumns": [{"name": "name","label": "Name","type": "string"},{"name": "email","label": "Email","type": "string"},{"name": "contactNumber","label": "Contact Number","type": "string"},{"name": "address.fullAddress","label": "Full Address","type": "string"},{"name": "address.addressLine","label": "Address Line","type": "string"},{"name": "address.city","label": "City","type": "string"},{"name": "address.state","label": "Country/State","type": "string"},{"name": "address.country","label": "Country","type": "string"},{"name": "address.zipCode","label": "Postcode/Zip","type": "string"},{"name": "website","label": "Website","type": "string"},{"name": "createdAt","label": "Created Date","type": "date"},{"name": "updatedAt","label": "Modified Date","type": "date"}],
      "defaultColumns": ["name", "contactNumber", "address"]
    },
    {
      "name": "insurer-user",
      "manageColumns": [{"name": "firstName","label": "First Name","type": "string"},{"name": "lastName","label": "Last Name","type": "string"},{"name": "email","label": "Email","type": "string"},{"name": "contactNumber","label": "Contact Number","type": "string"},{"name": "direct","label": "Direct","type": "string"},{"name": "jobTitle","label": "Job Title","type": "string"},{"name": "createdAt","label": "Created Date","type": "date"},{"name": "updatedAt","label": "Modified Date","type": "date"}],
      "defaultColumns": ["firstName","lastName","jobTitle"]
    },
    {
      "name": "insurer-policy",
      "manageColumns": [{"name": "insurerId","label": "Insurer Id","type": "string"},{"name": "clientId","label": "Client Id","type": "string"},{"name": "product","label": "Product","type": "string"},{"name": "policyPeriod","label": "Policy Period","type": "string"},{"name": "policyCurrency","label": "Policy Currency","type": "string"},{"name": "inceptionDate","label": "Inception Date","type": "date"},{"name": "expiryDate","label": "Expiry Date","type": "date"},{"name": "createdAt","label": "Created Date","type": "date"},{"name": "updatedAt","label": "Modified Date","type": "date"}],
      "defaultColumns": ["insurerId", "clientId", "product"]
    },
    {
      "name": "insurer-matrix",
      "manageColumns": [{"name": "insurerId","label": "Insurer Id","type": "string"},{"name": "clientId","label": "Client Id","type": "string"},{"name": "product","label": "Product","type": "string"},{"name": "policyPeriod","label": "Policy Period","type": "string"},{"name": "policyCurrency","label": "Policy Currency","type": "string"},{"name": "inceptionDate","label": "Inception Date","type": "date"},{"name": "expiryDate","label": "Expiry Date","type": "date"},{"name": "createdAt","label": "Created Date","type": "date"},{"name": "updatedAt","label": "Modified Date","type": "date"}],
      "defaultColumns": ["insurerId", "clientId", "product"]
    },
    {
      "name": "organization",
      "manageColumns": [],
      "defaultColumns": []
    },
    {
      "name": "overdue",
      "manageColumns": ["clientId", "debtorId", "applicationId", "updatedAt", "createdAt"],
      "defaultColumns": ["clientId", "debtorId", "applicationId"]
    },
    {
      "name": "report",
      "manageColumns": [],
      "defaultColumns": []
    },
    {
      "name": "task",
      "manageColumns": ["title","description","entityType","entityId","createdByType","createdById", "assigneeType", "assigneeId", "dueDate","isCompleted","updatedAt",  "createdAt"],
      "defaultColumns": ["title","description","entityType"]
    },
    {
      "name": "user",
      "manageColumns": [{"name": "name","label": "Name","type": "string"},{"name": "email","label": "Email","type": "string"},{"name": "contactNumber","label": "Contact Number","type": "string"},{"name": "role","label": "Role","type": "string"},{"name": "status","label": "Status","type": "string"},{"name": "createdAt","label": "Created Date","type": "date"},{"name": "updatedAt","label": "Modified Date","type": "date"}],
      "defaultColumns": ["name", "email","contactNumber"]
    }
  ]
}
